assets/classify_instructions.jpg
assets/compass.jpg
assets/instructions.jpg
assets/logo.png
assets/noClassifiedTargets.jpg
assets/noNextCropped.jpg
assets/noNextRaw.jpg
assets/noPreviousCropped.jpg
assets/noPreviousRaw.jpg
assets/oldLogo.png
assets/server_error.jpg
byu_auvsi_imaging_client-0.1.8.data/scripts/gui.py
lib/__init__.py
lib/client_rest.py
lib/tab0.py
lib/tab1.py
lib/tab2.py
lib/tab3.py
lib/tab4.py
lib/tab_tools.py
lib/test.py
byu_auvsi_imaging_client-0.1.8.dist-info/METADATA
byu_auvsi_imaging_client-0.1.8.dist-info/WHEEL
byu_auvsi_imaging_client-0.1.8.dist-info/entry_points.txt
byu_auvsi_imaging_client-0.1.8.dist-info/top_level.txt
byu_auvsi_imaging_client-0.1.8.dist-info/RECORD
