Metadata-Version: 2.1
Name: byu-auvsi-imaging-client
Version: 0.1.8
Summary: Imaging Client GUI for manual classification
Home-page: https://github.com/BYU-AUVSI/imaging
Author: BYU AUVSI Team
Author-email: tylerm15@gmail.com
License: UNKNOWN
Platform: UNKNOWN
Classifier: Programming Language :: Python :: 3
Classifier: Operating System :: OS Independent
Classifier: Programming Language :: Python :: 3.5
Classifier: Programming Language :: Python :: 3.6
Classifier: Programming Language :: Python :: 3.7
Requires-Dist: requests (==2.20.1)
Requires-Dist: pillow (==5.3.0)
Requires-Dist: opencv-python (==3.4.2.*)
Requires-Dist: ttkthemes (==2.2.0)
Requires-Dist: imutils (==0.5.2)
